[
    {
        "text": "Курс биткоина к доллару за апрель 2018",
        "date": "2018-04-01",
        "values": [7028, 6975, 7081, 7443, 6822, 6838, 6639, 6972, 7078, 6784, 
                   6864, 6956, 7836, 7873, 8051, 8360, 8051, 7940, 8146, 8355,
                   8820, 8847, 8818, 9146, 9568, 8778, 9223, 9041, 9398, 9395]
    },
    {
        "text": "Медали русской сборной на олимпиаде 2018",
        "date": "2018-02-01",
        "values": [0, 0, 0, 0, 0, 0, 0, 0, 6, 1,
                   0, 0, 2, 0, 0, 3, 1, 5, 0, 0,
                   3, 0, 2, 2, 1, 0, 0, 0]
    }
]
